<?xml version='1.0'?>
<tweets ID="2012-05-01">
<tweet>
<user>twitterapi</user>
<text>twitter site issuessome users may currently be experiencing site issues our engineers are working on httptco8mjhxmbu</text>
</tweet>
<tweet>
<user>Lastfm_Trends</user>
<text>with a new album by the offspring on the horizon we look at how their scrobbles shape up httptcopjg6p51m</text>
</tweet>
<tweet>
<user>Lastfm_Trends</user>
<text>rt lastfmpresents fancy some tips on who to see southwest4 check out some mustsee acts chosen by promoter jeff gray on lastfmtren</text>
</tweet>
<tweet>
<user>shitmydadsays</user>
<text>no i like talking i just hate people if i could find other shit to talk to id be all for it preorder new book httptconmnadknc</text>
</tweet>
<tweet>
<user>dubstream</user>
<text>jill palzkill woelfer named 2012 recipient of the university of washington graduate school medal httptcozfojpg3j</text>
</tweet>
</tweets>