<?xml version='1.0'?>
<tweets ID="2012-05-14">
<tweet>
<user>arhythmt</user>
<text>jfagans my pleasure chi is all about connections we move down in a week or so would love to meet up once were there</text>
</tweet>
<tweet>
<user>dubstream</user>
<text>jacob o wobbrock modeling and predicting pointing errors in two dimensions chi11 httptcoonv7g8lv</text>
</tweet>
<tweet>
<user>dubstream</user>
<text>alex jansen from the lab to the world lessons from extending a pointing technique for realworld use chi11 httptcopvdqg1ky</text>
</tweet>
<tweet>
<user>aweigend</user>
<text>byebye new york truly great meetup at httptcomfaqhp5x and yes hello seattle is it raining</text>
</tweet>
</tweets>