<?xml version='1.0'?>
<tweets ID="2012-09-05">
<tweet>
<user>UCBTweeter</user>
<text>indepth video lecture on apache pig by jco available for viewing nowsthanks for the great work jon httptcokfnkg6gv</text>
</tweet>
<tweet>
<user>danariely</user>
<text>harvard and the politics of largescale cheating httptcogrhjizlt</text>
</tweet>
<tweet>
<user>jimblomo</user>
<text>heading out to dc for wolframdatasummit speaking on visualizations in yelp learning about data connections to the real world</text>
</tweet>
<tweet>
<user>seekshreyas</user>
<text>blinkandumissit ajarrodkimber sampsoncollinssreally cant wait for it i love the 2 chucks and u guyz are real fans go chucks</text>
</tweet>
</tweets>