<?xml version='1.0'?>
<tweets ID="2012-12-02">
<tweet>
<user>zen_habits</user>
<text>rt aaronbaldassare zenhabits the one change that has improved my life the most has been to increasingly replace my opinions with cur</text>
</tweet>
<tweet>
<user>PoppedCulture</user>
<text>texter madness youth are much crazier and text messaging is an enabler of that says smith httptco1jwj1yvm</text>
</tweet>
<tweet>
<user>BestAt</user>
<text>rt princetweets2u just watched a video called gangnam style it was wild</text>
</tweet>
<tweet>
<user>dret</user>
<text>in rest you cannot really do anything with resources directly you can only request something to be done using the uniform interface</text>
</tweet>
<tweet>
<user>coldspire</user>
<text>went looking for something to boost my mood earlier today decided to play dead space 2 boy was that ever a dumb move</text>
</tweet>
<tweet>
<user>coldspire</user>
<text>devin plays a newage ballad surely not strapping young lad at the retinal circus with annoying buffering throbber httptcoaydno1em</text>
</tweet>
<tweet>
<user>TheCurrent</user>
<text>redefinition radio with kevinbeacham starts at 11 pm feat hip hop you wont hear anywhere else stream it httptcoz8lgzxjx</text>
</tweet>
<tweet>
<user>OaklandDD</user>
<text>rt berkeleylab berkeleylab part of energy team to receive up to 120m over 5 yrs to establish doe energy storagesbatteryhubs</text>
</tweet>
<tweet>
<user>qhardy</user>
<text>thesulk so much popserial killer songs you hear walkin after midnight all i have to do is dreamswant to buy a glass cutter</text>
</tweet>
<tweet>
<user>bakadesuyo</user>
<text>how can you quickly and easily increase confidence and reduce anxiety httptcoqfbc0c89</text>
</tweet>
<tweet>
<user>vaughanbell</user>
<text>fantastic an agency that matches jobs to the particular talents of autistic people httptcoofxemgcr via daviddobbs</text>
</tweet>
<tweet>
<user>bakadesuyo</user>
<text>is very confident not confident enough httptcogjfgfflc</text>
</tweet>
<tweet>
<user>chrisguillebeau</user>
<text>fellow shopper in downtown bangalore alternate caption sup httptcotm18ht5k</text>
</tweet>
<tweet>
<user>mjmauboussin</user>
<text>rt aswathdamodaran market unfazed by fiscal cliff or in denial erp for the sp 500 for dec 2012 at 602 it was 601 in nov 201</text>
</tweet>
<tweet>
<user>rtaibah</user>
<text>rt jenanmoussa my passport stamped by fsa at bab el salemeh crossing its a brand new stamp that reads new syria akhbar httpt</text>
</tweet>
<tweet>
<user>rtaibah</user>
<text>khaledsin any aware online community such practices would have been exposed and denounced quickly we are brain dead</text>
</tweet>
<tweet>
<user>rtaibah</user>
<text>ahmed grammar also after the colon</text>
</tweet>
<tweet>
<user>TheCurrent</user>
<text>happy birthday to the united states of americana billdeville celebrates 3 years of the us of americana this weekend</text>
</tweet>
<tweet>
<user>TheCurrent</user>
<text>there would be no uhited states of americana without you thanks for listeningsbilldeville usofa3rdbday httptcoteigxcxa</text>
</tweet>
<tweet>
<user>jayrosen_nyu</user>
<text>we werent even running in the same race at the quadrennial postmortem at harvard republicans go to obama school httptcowr7hl9ii</text>
</tweet>
<tweet>
<user>mattdipaola</user>
<text>rt cfcmedialab glad to have doctorow in our morning ideaboost session talking about his passions copyright writing and much more h</text>
</tweet>
<tweet>
<user>drewmo</user>
<text>pdlcomics thank you i really like yours too did justin tell you about friday applebees dance battles ooh good i see he did</text>
</tweet>
<tweet>
<user>raffi</user>
<text>bshine ive chosen to never learn how to make coffee to regulate myself i have to pay a crap load of cashshave to walk in the rain</text>
</tweet>
<tweet>
<user>raffi</user>
<text>bshine trying not to</text>
</tweet>
<tweet>
<user>TheCurrent</user>
<text>rt heids9 thecurrent united states of americana never disappoints</text>
</tweet>
<tweet>
<user>raffi</user>
<text>weather like today reminds me of one of my favorite itpnyu projectssthe polite umbrella httptcoo9rdm5fc</text>
</tweet>
<tweet>
<user>jayrosen_nyu</user>
<text>deisyenriquez jan 4</text>
</tweet>
<tweet>
<user>bakadesuyo</user>
<text>how can you become the leader of a group even when you dont know what youre talking about httptcorksvrk3b</text>
</tweet>
<tweet>
<user>rtaibah</user>
<text>especially berkeley onessrt darthnaderno one has better political analysis than taxi drivers they put political scientists to shame</text>
</tweet>
<tweet>
<user>drewmo</user>
<text>except that is for youss</text>
</tweet>
<tweet>
<user>myy_precious</user>
<text>cleaned my laptop screen after ages shine bright like a diamond rihanna laptops lazygrad</text>
</tweet>
<tweet>
<user>zen_habits</user>
<text>mathematicians new epiphany adding transcendental numbers pise together make them more delicious</text>
</tweet>
<tweet>
<user>myy_precious</user>
<text>seekshreyas hahah this song shine bright like a diamond by rihanna is on top 10 on spotify clearly you dont listen to pop p</text>
</tweet>
<tweet>
<user>gilgul</user>
<text>jonathanstray depends on the graph could be rt or friendship</text>
</tweet>
</tweets>