<?xml version='1.0'?>
<tweets ID="2012-09-26">
<tweet>
<user>seekshreyas</user>
<text>myypreciousstake a sip of beer too it might make it easier</text>
</tweet>
<tweet>
<user>petewarden</user>
<text>the secrets of community building new post community is spelled with 3 ps httptcovbtlbhd3 great post happy birthday micah</text>
</tweet>
<tweet>
<user>Stata</user>
<text>if you are interested here is a short guide to creating maps with stata by friedrich huebler we came across httptcooc58kfui</text>
</tweet>
<tweet>
<user>SenBennetCO</user>
<text>meet itriage a co startup that went from 2 to 100 employees in 5 years proof that innovation drives job growth httptcoruvxidus</text>
</tweet>
<tweet>
<user>ibfrog</user>
<text>profootballtalk any word on the cheap shot and scuffle between jennings and browner on mnf</text>
</tweet>
<tweet>
<user>twitterapi</user>
<text>tweetmeme is transitioning their old button to the tweet button in the next 24hrs read more a tweetmeme farewell httptcotoobqndk</text>
</tweet>
<tweet>
<user>danariely</user>
<text>another worrisome results on gender differencesshttptcoah4bz4gc</text>
</tweet>
<tweet>
<user>seekshreyas</user>
<text>rt worrydreamslearnable programming designing a programming system for understanding programsshttptconhiei7g0</text>
</tweet>
<tweet>
<user>seekshreyas</user>
<text>rt rjs this image from bret victors essay on learnable programming tugs the heartstrings httptcogrx2jkn7</text>
</tweet>
</tweets>