<?xml version='1.0'?>
<tweets ID="2012-09-18">
<tweet>
<user>ThePBXGuy</user>
<text>check out my presentation on carrier innovation goals on our blog httptco3scxvywl</text>
</tweet>
<tweet>
<user>ThePBXGuy</user>
<text>krmc if you have some time check this out httptcowhemr6ry</text>
</tweet>
<tweet>
<user>ThePBXGuy</user>
<text>tatacomm check out our new blog post based on tc3 httptcowhemr6ry</text>
</tweet>
<tweet>
<user>ThePBXGuy</user>
<text>derekkerton check out our blog post on tc3 httptcowhemr6ry</text>
</tweet>
<tweet>
<user>ThePBXGuy</user>
<text>telecomcouncil check out our blog post about tc3 httptcowhemr6ry</text>
</tweet>
<tweet>
<user>ThePBXGuy</user>
<text>junipernetworks check out our blog post about tc3 httptcowhemr6ry</text>
</tweet>
<tweet>
<user>ThePBXGuy</user>
<text>orangebusiness check out our blog post about tc3 httptcowhemr6ry</text>
</tweet>
<tweet>
<user>zen_habits</user>
<text>what seems nasty painful or evil can become a source of beauty joysstrength if faced with an open mind henry miller</text>
</tweet>
<tweet>
<user>BerkeleyISchool</user>
<text>check out the videos from our big datastwitter class httptco4o9zhdxr last week kostas on how twitter trends are computed</text>
</tweet>
<tweet>
<user>BerkeleyISchool</user>
<text>we also have video from the social data revolution course with aweigend httptcoeodzm2ne socialdata</text>
</tweet>
<tweet>
<user>petewarden</user>
<text>rt ieure tried this fantasy football thing but my team was devoured by orcs in the red mountains not sure i see the appeal</text>
</tweet>
</tweets>