<?xml version='1.0'?>
<tweets ID="2012-09-20">
<tweet>
<user>hoofnagle</user>
<text>creative types are worth hiring in a call centerssociopaths are put on the management track httptcokrei1zn7</text>
</tweet>
<tweet>
<user>ryanmcadam</user>
<text>a candid proposal from an advertising firms creative director via mcsweenysshttptcogha9kxar</text>
</tweet>
<tweet>
<user>open_michigan</user>
<text>stop by north quads space 2435 tomorrow from 15 for some preweekend studying dropin tutoring and more umich</text>
</tweet>
<tweet>
<user>Padday</user>
<text>haggersnash ianbetteridge what same points you dont think websmobile technology will dramatically change marketing within next decade</text>
</tweet>
<tweet>
<user>RobertCialdini</user>
<text>steve martin cmct published in the harvard business review harvardbiz scienceofyes httptcoqpbuwpik ev</text>
</tweet>
<tweet>
<user>OaklandDD</user>
<text>rt citrisnews today 2 pm in qualcomm cafe kqed quest viewing party and per peterson will talk about the future of nuclear energy ht</text>
</tweet>
<tweet>
<user>ThePBXGuy</user>
<text>rakeshlobster om pure awesome</text>
</tweet>
<tweet>
<user>SenBennetCO</user>
<text>another example of why its time to pass the wind ptc before we lose any more jobs httptcohbs7jhna</text>
</tweet>
<tweet>
<user>OaklandDD</user>
<text>prof dick karp just showed renderings for new home of simons institute for the theory of computing cal looks great httptcovpokfttz</text>
</tweet>
</tweets>