<?xml version='1.0'?>
<tweets ID="2012-11-15">
<tweet>
<user>st_ffen</user>
<text>in light of the petraeus scandal is anything we do online really private httptcoew4f2opi</text>
</tweet>
<tweet>
<user>raffi</user>
<text>kevinlee94 thanks im so sorry i missed it i really look forward to giving the cs10 lecture every yearsso im totally bummed out</text>
</tweet>
<tweet>
<user>jwboyer19</user>
<text>daveboutcher congrats i thinkhope</text>
</tweet>
<tweet>
<user>ferociousj</user>
<text>if i cant find three people to coop some halo 4 campaign with tonight i think it might be skyfall time</text>
</tweet>
<tweet>
<user>qhardy</user>
<text>my books arent exactly plotdriven they are about people with guns in dire situations elmore leonard mr selfaware</text>
</tweet>
<tweet>
<user>jwboyer19</user>
<text>debuginfo is the worst thing about building kernels eversi just want to go to sleep</text>
</tweet>
<tweet>
<user>chouse</user>
<text>rt opsview just published our latest case study from open systems technologies in the states excellent example of how msps can uhttp</text>
</tweet>
<tweet>
<user>jaredpolis</user>
<text>rt roseveleth will 3d printing effect the economy trick question it already is httptcorzrrgypw</text>
</tweet>
<tweet>
<user>smunson</user>
<text>want to come work on hci at uw new oneyear mhcid program site at httptcoprigimj8 hcde program details at httptcobztsxteu</text>
</tweet>
<tweet>
<user>zephoria</user>
<text>why am i so good at breaking technology grumblegrumblegrumble</text>
</tweet>
<tweet>
<user>dubstream</user>
<text>rt uwitech uw dubstream launches new 1 year masters in humancomputer interactionsdesign 1st incoming class autumn 2013 httpt</text>
</tweet>
<tweet>
<user>petewarden</user>
<text>covert i know that one well its right outside my front door</text>
</tweet>
<tweet>
<user>petewarden</user>
<text>covert it has next wednesday evening any good</text>
</tweet>
<tweet>
<user>BestAt</user>
<text>rt chrisdelia oh god is testing you no its really just that everyone doesnt like you so life is harder</text>
</tweet>
<tweet>
<user>chouse</user>
<text>ewantoo yup turned out to be streamified dumping that extension and left a negative review at the chrome store unacceptable</text>
</tweet>
<tweet>
<user>drewmo</user>
<text>this is what a good dad looks like httptcowrhubd6d</text>
</tweet>
<tweet>
<user>bgurley</user>
<text>only in san franciscossfo httptcoykzgwnk3</text>
</tweet>
<tweet>
<user>johnbattelle</user>
<text>philgyford jeez i forgot about that and i was going to give it to the smithsonian</text>
</tweet>
<tweet>
<user>hungtruong</user>
<text>thatklickitat no offense but congrats</text>
</tweet>
<tweet>
<user>dubstream</user>
<text>rt tomfurt uw dubstream launches new 1 year masters in humancomputer interactionsdesign 1st incoming class autumn 2013 httpt</text>
</tweet>
<tweet>
<user>vanschewick</user>
<text>rt levjoy att relents on blocking facetime and violating netneutrality kinda sorta maybe httptcouigh9jws</text>
</tweet>
<tweet>
<user>thinkingfish</user>
<text>its that time of the year again i just donated to wikipedia keepitfree httptco8xlbicjx</text>
</tweet>
<tweet>
<user>bigdata</user>
<text>one reason to avoid tattoos new biometric vision researchers would love playing with this data httptcoen4fz7jwshttptcopupabp1m</text>
</tweet>
<tweet>
<user>jwboyer19</user>
<text>i hate squirrelss that is all</text>
</tweet>
<tweet>
<user>zephoria</user>
<text>im seriously honored and humbled to be inducted into the sxsw interactive hall of fame blush httptcofmtolwdr</text>
</tweet>
<tweet>
<user>BerkeleyISchool</user>
<text>congratulations to our alum zephoria the newest member of the sxsw interactive hall of fame httptcokv7hy3xx</text>
</tweet>
<tweet>
<user>drewmo</user>
<text>dataisplural on behalf of all the beautifuls allow me to apologize</text>
</tweet>
<tweet>
<user>GeekKevin</user>
<text>rt thumb plz retweetsnominate thumb for the best app ever awards best time killersbest social app httptcoudhxrstn</text>
</tweet>
<tweet>
<user>myy_precious</user>
<text>i want a doll</text>
</tweet>
</tweets>